MdXLogseqTODOSync/MdXLogseqTODOSync.py
MdXLogseqTODOSync/__init__.py
MdXLogseqTODOSync/__main__.py
MdXLogseqTODOSync-0.1.0.dist-info/LICENSE.md
MdXLogseqTODOSync-0.1.0.dist-info/METADATA
MdXLogseqTODOSync-0.1.0.dist-info/WHEEL
MdXLogseqTODOSync-0.1.0.dist-info/entry_points.txt
MdXLogseqTODOSync-0.1.0.dist-info/top_level.txt
MdXLogseqTODOSync-0.1.0.dist-info/RECORD
