Metadata-Version: 2.1
Name: MdXLogseqTODOSync
Version: 0.1.0
Summary: Script to always sync a Logseq TODO list with a markdown file
Home-page: https://github.com/thiswillbeyourgithub/MdXLogseqTODOSync
License: GPLv3
Keywords: logseq,todo,list,markdown,md,organization,productivity
Classifier: Programming Language :: Python :: 3
Classifier: License :: OSI Approved :: GNU General Public License v3 (GPLv3)
Classifier: Operating System :: OS Independent
Requires-Python: >=3.11
License-File: LICENSE.md
Requires-Dist: fire>=0.6.0
Requires-Dist: beartype>=0.18.5
Requires-Dist: LogseqMarkdownParser>=3.3
